pfc_util/__init__.py
pfc_util/history.py
pfc_util/pfc.py
pfc_util/core/__evolution.py
pfc_util/core/__init__.py
pfc_util/core/abc.py
pfc_util/core/base.py
pfc_util/core/version.py
pfc_util/core/evolution/__init__.py
pfc_util/core/evolution/base.py
pfc_util/core/evolution/conserved.py
pfc_util/core/evolution/mu.py
pfc_util/core/evolution/relax.py
pfc_util/core/evolution/relax_base.py
pfc_util/extra/__gaussian.py
pfc_util/extra/__init__.py
pfc_util/extra/__pfc6.py
pfc_util/extra/pfc6/__init__.py
pfc_util/extra/pfc6/base.py
pfc_util/extra/pfc6/conserved.py
pfc_util/extra/pfc6/mu.py
pfc_util/extra/pfc6/relax.py
pfc_util/legacy/__init__.py
pfc_util/legacy/pfc.py
pfc_util/legacy/pfc_im.py
pfc_util/legacy/profile_prompt/__init__.py
pfc_util/legacy/profile_prompt/editor_prompt.py
pfc_util/legacy/profile_prompt/prompt.py
pfc_util/toolkit/__init__.py
pfc_util/toolkit/ortho_lattice_generator.py
pfc_util/toolkit/rotated.py
pfc_util/toolkit/static.py
pfc_util/toolkit/_res/__init__.py
pfc_util/toolkit/_res/uc_eps0.01.field
pfc_util/toolkit/_res/uc_eps0.01_liq.field
pfc_util/toolkit/_res/uc_eps0.02.field
pfc_util/toolkit/_res/uc_eps0.02_liq.field
pfc_util/toolkit/_res/uc_eps0.04.field
pfc_util/toolkit/_res/uc_eps0.04_liq.field
pfc_util/toolkit/_res/uc_eps0.06.field
pfc_util/toolkit/_res/uc_eps0.06_liq.field
pfc_util/toolkit/_res/uc_eps0.08.field
pfc_util/toolkit/_res/uc_eps0.08_liq.field
pfc_util/toolkit/_res/uc_eps0.1.field
pfc_util/toolkit/_res/uc_eps0.11.field
pfc_util/toolkit/_res/uc_eps0.11_liq.field
pfc_util/toolkit/_res/uc_eps0.12.field
pfc_util/toolkit/_res/uc_eps0.12_liq.field
pfc_util/toolkit/_res/uc_eps0.13.field
pfc_util/toolkit/_res/uc_eps0.13_liq.field
pfc_util/toolkit/_res/uc_eps0.14.field
pfc_util/toolkit/_res/uc_eps0.14_liq.field
pfc_util/toolkit/_res/uc_eps0.15.field
pfc_util/toolkit/_res/uc_eps0.15_liq.field
pfc_util/toolkit/_res/uc_eps0.17.field
pfc_util/toolkit/_res/uc_eps0.17_liq.field
pfc_util/toolkit/_res/uc_eps0.1_liq.field
pfc_util-0.4.12.dist-info/LICENSE
pfc_util-0.4.12.dist-info/METADATA
pfc_util-0.4.12.dist-info/WHEEL
pfc_util-0.4.12.dist-info/top_level.txt
pfc_util-0.4.12.dist-info/RECORD
