Metadata-Version: 2.1
Name: pfc-util
Version: 0.4.12
Summary: package for PFC (phase field crystal) simulations
Home-page: https://github.com/michael-960/pfc_util
Author: Michael Wang
Author-email: mike.wang96029@gmail.com
Project-URL: Bug Tracker, https://github.com/michael-960/pfc_util/issues
Classifier: Programming Language :: Python :: 3
Classifier: License :: OSI Approved :: MIT License
Classifier: Operating System :: OS Independent
Requires-Python: >=3.7
License-File: LICENSE
Requires-Dist: numpy (>=1.21.2)
Requires-Dist: scipy (>=1.7)
Requires-Dist: pyfftw (>=0.12)
Requires-Dist: matplotlib (>=3.5.1)
Requires-Dist: torusgrid (>=0.4.8)
Requires-Dist: rich (>=12.4.0)
